[
  {
    "cluster_info": {
      "cores_per_node": 0,
      "memory_per_node_gb": 0,
      "network_bandwidth_gbps": 0,
      "network_latency_ms": 0,
      "num_nodes": 0,
      "threads_per_node": 0
    }
  },
  {
    "program_info": {
      "arrays_info": [
        {
          "dimensions": [
            8
          ],
          "element_size_bytes": 4,
          "name": "f0_38_a"
        },
        {
          "dimensions": [
            8
          ],
          "element_size_bytes": 4,
          "name": "f0_38_c"
        },
        {
          "dimensions": [
            16
          ],
          "element_size_bytes": 4,
          "name": "f0_91_a"
        },
        {
          "dimensions": [
            16
          ],
          "element_size_bytes": 4,
          "name": "f0_91_c"
        },
        {
          "dimensions": [
            16
          ],
          "element_size_bytes": 4,
          "name": "f0_143_a"
        },
        {
          "dimensions": [
            16
          ],
          "element_size_bytes": 4,
          "name": "f0_143_c"
        },
        {
          "dimensions": [
            16
          ],
          "element_size_bytes": 4,
          "name": "f0_196_a"
        },
        {
          "dimensions": [
            16
          ],
          "element_size_bytes": 4,
          "name": "f0_196_c"
        },
        {
          "dimensions": [
            16
          ],
          "element_size_bytes": 4,
          "name": "f0_250_a"
        },
        {
          "dimensions": [
            16
          ],
          "element_size_bytes": 4,
          "name": "f0_250_c"
        },
        {
          "dimensions": [
            16
          ],
          "element_size_bytes": 4,
          "name": "f0_305_a"
        },
        {
          "dimensions": [
            16
          ],
          "element_size_bytes": 4,
          "name": "f0_305_c"
        },
        {
          "dimensions": [
            16
          ],
          "element_size_bytes": 4,
          "name": "f0_358_a"
        },
        {
          "dimensions": [
            16
          ],
          "element_size_bytes": 4,
          "name": "f0_358_c"
        },
        {
          "dimensions": [
            24
          ],
          "element_size_bytes": 4,
          "name": "f0_412_a"
        },
        {
          "dimensions": [
            24
          ],
          "element_size_bytes": 4,
          "name": "f0_412_c"
        },
        {
          "dimensions": [
            24
          ],
          "element_size_bytes": 4,
          "name": "f0_466_a"
        },
        {
          "dimensions": [
            24
          ],
          "element_size_bytes": 4,
          "name": "f0_466_c"
        },
        {
          "dimensions": [
            50
          ],
          "element_size_bytes": 4,
          "name": "f0_523_a"
        },
        {
          "dimensions": [
            50
          ],
          "element_size_bytes": 4,
          "name": "f0_523_c"
        },
        {
          "dimensions": [
            1
          ],
          "element_size_bytes": 4,
          "name": "f0_573_ar"
        }
      ],
      "average_parallel_line_executions": 46.55,
      "directives": {
        "across": [
          {
            "array_id": 0,
            "communication_pattern": "NEAREST_NEIGHBOR",
            "line": 63,
            "width": [
              [
                0,
                1,
                1
              ]
            ]
          },
          {
            "array_id": 2,
            "communication_pattern": "NEAREST_NEIGHBOR",
            "line": 115,
            "width": [
              [
                0,
                0,
                1
              ]
            ]
          },
          {
            "array_id": 4,
            "communication_pattern": "NEAREST_NEIGHBOR",
            "line": 167,
            "width": [
              [
                0,
                1,
                0
              ]
            ]
          },
          {
            "array_id": 6,
            "communication_pattern": "NEAREST_NEIGHBOR",
            "line": 221,
            "width": [
              [
                0,
                2,
                2
              ]
            ]
          },
          {
            "array_id": 8,
            "communication_pattern": "NEAREST_NEIGHBOR",
            "line": 275,
            "width": [
              [
                0,
                0,
                2
              ]
            ]
          },
          {
            "array_id": 10,
            "communication_pattern": "NEAREST_NEIGHBOR",
            "line": 329,
            "width": [
              [
                0,
                2,
                0
              ]
            ]
          },
          {
            "array_id": 12,
            "communication_pattern": "NEAREST_NEIGHBOR",
            "line": 383,
            "width": [
              [
                0,
                3,
                3
              ]
            ]
          },
          {
            "array_id": 14,
            "communication_pattern": "NEAREST_NEIGHBOR",
            "line": 437,
            "width": [
              [
                0,
                0,
                3
              ]
            ]
          },
          {
            "array_id": 16,
            "communication_pattern": "NEAREST_NEIGHBOR",
            "line": 492,
            "width": [
              [
                0,
                3,
                0
              ]
            ]
          },
          {
            "array_id": 18,
            "communication_pattern": "NEAREST_NEIGHBOR",
            "line": 548,
            "width": [
              [
                0,
                11,
                11
              ]
            ]
          }
        ],
        "distribute": [
          {
            "array_id": 0,
            "distribution_spec": [
              "*"
            ],
            "line": 41
          },
          {
            "array_id": 2,
            "distribution_spec": [
              "*"
            ],
            "line": 94
          },
          {
            "array_id": 4,
            "distribution_spec": [
              "*"
            ],
            "line": 146
          },
          {
            "array_id": 6,
            "distribution_spec": [
              "*"
            ],
            "line": 199
          },
          {
            "array_id": 8,
            "distribution_spec": [
              "*"
            ],
            "line": 253
          },
          {
            "array_id": 10,
            "distribution_spec": [
              "*"
            ],
            "line": 307
          },
          {
            "array_id": 12,
            "distribution_spec": [
              "*"
            ],
            "line": 361
          },
          {
            "array_id": 14,
            "distribution_spec": [
              "*"
            ],
            "line": 415
          },
          {
            "array_id": 16,
            "distribution_spec": [
              "*"
            ],
            "line": 469
          },
          {
            "array_id": 18,
            "distribution_spec": [
              "*"
            ],
            "line": 526
          }
        ],
        "parallel": [
          {
            "acrosses": [],
            "computational_intensity": 1.0,
            "iterations_count": [
              1
            ],
            "line": 57,
            "loops_count": 1,
            "reductions": [],
            "remote_accesses": [],
            "shadow_renews": []
          },
          {
            "acrosses": [],
            "computational_intensity": 1.0,
            "iterations_count": [
              0
            ],
            "line": 63,
            "loops_count": 1,
            "reductions": [],
            "remote_accesses": [],
            "shadow_renews": [
              0
            ]
          },
          {
            "acrosses": [],
            "computational_intensity": 0.5,
            "iterations_count": [
              1
            ],
            "line": 68,
            "loops_count": 1,
            "reductions": [
              0
            ],
            "remote_accesses": [],
            "shadow_renews": []
          },
          {
            "acrosses": [],
            "computational_intensity": 1.0,
            "iterations_count": [
              1
            ],
            "line": 110,
            "loops_count": 1,
            "reductions": [],
            "remote_accesses": [],
            "shadow_renews": []
          },
          {
            "acrosses": [],
            "computational_intensity": 0.6666666666666666,
            "iterations_count": [
              0
            ],
            "line": 115,
            "loops_count": 1,
            "reductions": [],
            "remote_accesses": [],
            "shadow_renews": [
              1
            ]
          },
          {
            "acrosses": [],
            "computational_intensity": 0.5,
            "iterations_count": [
              0
            ],
            "line": 120,
            "loops_count": 1,
            "reductions": [
              1
            ],
            "remote_accesses": [],
            "shadow_renews": []
          },
          {
            "acrosses": [],
            "computational_intensity": 1.0,
            "iterations_count": [
              1
            ],
            "line": 162,
            "loops_count": 1,
            "reductions": [],
            "remote_accesses": [],
            "shadow_renews": []
          },
          {
            "acrosses": [],
            "computational_intensity": 0.6666666666666666,
            "iterations_count": [
              0
            ],
            "line": 167,
            "loops_count": 1,
            "reductions": [],
            "remote_accesses": [],
            "shadow_renews": [
              2
            ]
          },
          {
            "acrosses": [],
            "computational_intensity": 0.5,
            "iterations_count": [
              0
            ],
            "line": 172,
            "loops_count": 1,
            "reductions": [
              2
            ],
            "remote_accesses": [],
            "shadow_renews": []
          },
          {
            "acrosses": [],
            "computational_intensity": 1.0,
            "iterations_count": [
              1
            ],
            "line": 216,
            "loops_count": 1,
            "reductions": [],
            "remote_accesses": [],
            "shadow_renews": []
          },
          {
            "acrosses": [],
            "computational_intensity": 1.4,
            "iterations_count": [
              0
            ],
            "line": 221,
            "loops_count": 1,
            "reductions": [],
            "remote_accesses": [],
            "shadow_renews": [
              3
            ]
          },
          {
            "acrosses": [],
            "computational_intensity": 0.5,
            "iterations_count": [
              1
            ],
            "line": 226,
            "loops_count": 1,
            "reductions": [
              3
            ],
            "remote_accesses": [],
            "shadow_renews": []
          },
          {
            "acrosses": [],
            "computational_intensity": 1.0,
            "iterations_count": [
              1
            ],
            "line": 270,
            "loops_count": 1,
            "reductions": [],
            "remote_accesses": [],
            "shadow_renews": []
          },
          {
            "acrosses": [],
            "computational_intensity": 1.0,
            "iterations_count": [
              0
            ],
            "line": 275,
            "loops_count": 1,
            "reductions": [],
            "remote_accesses": [],
            "shadow_renews": [
              4
            ]
          },
          {
            "acrosses": [],
            "computational_intensity": 0.5,
            "iterations_count": [
              1
            ],
            "line": 280,
            "loops_count": 1,
            "reductions": [
              4
            ],
            "remote_accesses": [],
            "shadow_renews": []
          },
          {
            "acrosses": [],
            "computational_intensity": 1.0,
            "iterations_count": [
              1
            ],
            "line": 324,
            "loops_count": 1,
            "reductions": [],
            "remote_accesses": [],
            "shadow_renews": []
          },
          {
            "acrosses": [],
            "computational_intensity": 1.0,
            "iterations_count": [
              0
            ],
            "line": 329,
            "loops_count": 1,
            "reductions": [],
            "remote_accesses": [],
            "shadow_renews": [
              5
            ]
          },
          {
            "acrosses": [],
            "computational_intensity": 0.5,
            "iterations_count": [
              1
            ],
            "line": 334,
            "loops_count": 1,
            "reductions": [
              5
            ],
            "remote_accesses": [],
            "shadow_renews": []
          },
          {
            "acrosses": [],
            "computational_intensity": 1.0,
            "iterations_count": [
              1
            ],
            "line": 378,
            "loops_count": 1,
            "reductions": [],
            "remote_accesses": [],
            "shadow_renews": []
          },
          {
            "acrosses": [],
            "computational_intensity": 1.5714285714285714,
            "iterations_count": [
              0
            ],
            "line": 383,
            "loops_count": 1,
            "reductions": [],
            "remote_accesses": [],
            "shadow_renews": [
              6
            ]
          },
          {
            "acrosses": [],
            "computational_intensity": 0.5,
            "iterations_count": [
              1
            ],
            "line": 388,
            "loops_count": 1,
            "reductions": [
              6
            ],
            "remote_accesses": [],
            "shadow_renews": []
          },
          {
            "acrosses": [],
            "computational_intensity": 1.0,
            "iterations_count": [
              1
            ],
            "line": 432,
            "loops_count": 1,
            "reductions": [],
            "remote_accesses": [],
            "shadow_renews": []
          },
          {
            "acrosses": [],
            "computational_intensity": 1.25,
            "iterations_count": [
              0
            ],
            "line": 437,
            "loops_count": 1,
            "reductions": [],
            "remote_accesses": [],
            "shadow_renews": [
              7
            ]
          },
          {
            "acrosses": [],
            "computational_intensity": 0.5,
            "iterations_count": [
              1
            ],
            "line": 442,
            "loops_count": 1,
            "reductions": [
              7
            ],
            "remote_accesses": [],
            "shadow_renews": []
          },
          {
            "acrosses": [],
            "computational_intensity": 1.0,
            "iterations_count": [
              1
            ],
            "line": 487,
            "loops_count": 1,
            "reductions": [],
            "remote_accesses": [],
            "shadow_renews": []
          },
          {
            "acrosses": [],
            "computational_intensity": 1.25,
            "iterations_count": [
              0
            ],
            "line": 492,
            "loops_count": 1,
            "reductions": [],
            "remote_accesses": [],
            "shadow_renews": [
              8
            ]
          },
          {
            "acrosses": [],
            "computational_intensity": 0.5,
            "iterations_count": [
              1
            ],
            "line": 497,
            "loops_count": 1,
            "reductions": [
              8
            ],
            "remote_accesses": [],
            "shadow_renews": []
          },
          {
            "acrosses": [],
            "computational_intensity": 1.0,
            "iterations_count": [
              1
            ],
            "line": 543,
            "loops_count": 1,
            "reductions": [],
            "remote_accesses": [],
            "shadow_renews": []
          },
          {
            "acrosses": [],
            "computational_intensity": 1.5714285714285714,
            "iterations_count": [
              0
            ],
            "line": 548,
            "loops_count": 1,
            "reductions": [],
            "remote_accesses": [],
            "shadow_renews": [
              9
            ]
          },
          {
            "acrosses": [],
            "computational_intensity": 0.5,
            "iterations_count": [
              1
            ],
            "line": 553,
            "loops_count": 1,
            "reductions": [
              9
            ],
            "remote_accesses": [],
            "shadow_renews": []
          }
        ],
        "reduction": [
          {
            "elements_count": 1,
            "line": 68,
            "operation": "min",
            "reduction_type": "SCALAR",
            "size_bytes": 4
          },
          {
            "elements_count": 1,
            "line": 120,
            "operation": "min",
            "reduction_type": "SCALAR",
            "size_bytes": 4
          },
          {
            "elements_count": 1,
            "line": 172,
            "operation": "min",
            "reduction_type": "SCALAR",
            "size_bytes": 4
          },
          {
            "elements_count": 1,
            "line": 226,
            "operation": "min",
            "reduction_type": "SCALAR",
            "size_bytes": 4
          },
          {
            "elements_count": 1,
            "line": 280,
            "operation": "min",
            "reduction_type": "SCALAR",
            "size_bytes": 4
          },
          {
            "elements_count": 1,
            "line": 334,
            "operation": "min",
            "reduction_type": "SCALAR",
            "size_bytes": 4
          },
          {
            "elements_count": 1,
            "line": 388,
            "operation": "min",
            "reduction_type": "SCALAR",
            "size_bytes": 4
          },
          {
            "elements_count": 1,
            "line": 442,
            "operation": "min",
            "reduction_type": "SCALAR",
            "size_bytes": 4
          },
          {
            "elements_count": 1,
            "line": 497,
            "operation": "min",
            "reduction_type": "SCALAR",
            "size_bytes": 4
          },
          {
            "elements_count": 1,
            "line": 553,
            "operation": "min",
            "reduction_type": "SCALAR",
            "size_bytes": 4
          }
        ],
        "remote_access": null,
        "shadow_renew": null
      },
      "launch_grid": {
        "dimensions": [
          0,
          0,
          0
        ],
        "total_processes": 0
      },
      "parallel_execution_fraction": 0.3950774453638871,
      "sequential_execution_time_sec": 0.0
    }
  }
]
