[
  {
    "cluster_info": {
      "cores_per_node": 0,
      "memory_per_node_gb": 0,
      "network_bandwidth_gbps": 0,
      "network_latency_ms": 0,
      "num_nodes": 0,
      "threads_per_node": 0
    }
  },
  {
    "program_info": {
      "arrays_info": [
        {
          "dimensions": [
            16
          ],
          "element_size_bytes": 4,
          "name": "f0_52_a"
        },
        {
          "dimensions": [
            16
          ],
          "element_size_bytes": 4,
          "name": "f0_52_c"
        },
        {
          "dimensions": [
            16
          ],
          "element_size_bytes": 4,
          "name": "f0_90_a"
        },
        {
          "dimensions": [
            16
          ],
          "element_size_bytes": 4,
          "name": "f0_90_c"
        },
        {
          "dimensions": [
            16
          ],
          "element_size_bytes": 4,
          "name": "f0_128_a"
        },
        {
          "dimensions": [
            16
          ],
          "element_size_bytes": 4,
          "name": "f0_128_c"
        },
        {
          "dimensions": [
            16
          ],
          "element_size_bytes": 4,
          "name": "f0_170_a"
        },
        {
          "dimensions": [
            16
          ],
          "element_size_bytes": 4,
          "name": "f0_170_c"
        },
        {
          "dimensions": [
            16
          ],
          "element_size_bytes": 4,
          "name": "f0_212_a"
        },
        {
          "dimensions": [
            16
          ],
          "element_size_bytes": 4,
          "name": "f0_212_c"
        },
        {
          "dimensions": [
            8
          ],
          "element_size_bytes": 4,
          "name": "f0_255_a"
        },
        {
          "dimensions": [
            8
          ],
          "element_size_bytes": 4,
          "name": "f0_255_c"
        },
        {
          "dimensions": [
            16
          ],
          "element_size_bytes": 4,
          "name": "f0_295_a"
        },
        {
          "dimensions": [
            16
          ],
          "element_size_bytes": 4,
          "name": "f0_295_c"
        },
        {
          "dimensions": [
            16
          ],
          "element_size_bytes": 4,
          "name": "f0_341_a"
        },
        {
          "dimensions": [
            16
          ],
          "element_size_bytes": 4,
          "name": "f0_341_c"
        },
        {
          "dimensions": [
            16
          ],
          "element_size_bytes": 4,
          "name": "f0_385_a"
        },
        {
          "dimensions": [
            16
          ],
          "element_size_bytes": 4,
          "name": "f0_385_c"
        },
        {
          "dimensions": [
            16
          ],
          "element_size_bytes": 4,
          "name": "f0_429_a"
        },
        {
          "dimensions": [
            16
          ],
          "element_size_bytes": 4,
          "name": "f0_429_c"
        },
        {
          "dimensions": [
            16
          ],
          "element_size_bytes": 4,
          "name": "f0_475_a"
        },
        {
          "dimensions": [
            16
          ],
          "element_size_bytes": 4,
          "name": "f0_475_c"
        },
        {
          "dimensions": [
            16
          ],
          "element_size_bytes": 4,
          "name": "f0_523_a"
        },
        {
          "dimensions": [
            16
          ],
          "element_size_bytes": 4,
          "name": "f0_523_c"
        },
        {
          "dimensions": [
            16
          ],
          "element_size_bytes": 4,
          "name": "f0_571_a"
        },
        {
          "dimensions": [
            16
          ],
          "element_size_bytes": 4,
          "name": "f0_571_c"
        },
        {
          "dimensions": [
            16
          ],
          "element_size_bytes": 4,
          "name": "f0_633_a"
        },
        {
          "dimensions": [
            16
          ],
          "element_size_bytes": 4,
          "name": "f0_633_c"
        },
        {
          "dimensions": [
            16
          ],
          "element_size_bytes": 4,
          "name": "f0_635_b"
        },
        {
          "dimensions": [
            16
          ],
          "element_size_bytes": 4,
          "name": "f0_635_cl"
        },
        {
          "dimensions": [
            16
          ],
          "element_size_bytes": 4,
          "name": "f0_700_a"
        },
        {
          "dimensions": [
            16
          ],
          "element_size_bytes": 4,
          "name": "f0_700_c"
        },
        {
          "dimensions": [
            16
          ],
          "element_size_bytes": 4,
          "name": "f0_767_a"
        },
        {
          "dimensions": [
            16
          ],
          "element_size_bytes": 4,
          "name": "f0_767_c"
        },
        {
          "dimensions": [
            1
          ],
          "element_size_bytes": 4,
          "name": "f0_840_ar"
        },
        {
          "dimensions": [
            1
          ],
          "element_size_bytes": 4,
          "name": "f0_853_ar"
        },
        {
          "dimensions": [
            1
          ],
          "element_size_bytes": 4,
          "name": "f0_869_ar"
        },
        {
          "dimensions": [
            1
          ],
          "element_size_bytes": 4,
          "name": "f0_885_ar"
        },
        {
          "dimensions": [
            1
          ],
          "element_size_bytes": 4,
          "name": "f0_897_ar"
        },
        {
          "dimensions": [
            1
          ],
          "element_size_bytes": 4,
          "name": "f0_909_ar"
        }
      ],
      "average_parallel_line_executions": 13.245454545454546,
      "directives": {
        "across": null,
        "align": [
          {
            "line": 639,
            "rules": [
              [
                0,
                1,
                0
              ]
            ],
            "source_array_id": 28,
            "target_array_id": 26
          }
        ],
        "distribute": [
          {
            "array_id": 0,
            "distribution_spec": [
              "*"
            ],
            "line": 55
          },
          {
            "array_id": 2,
            "distribution_spec": [
              "*"
            ],
            "line": 93
          },
          {
            "array_id": 4,
            "distribution_spec": [
              "*"
            ],
            "line": 131
          },
          {
            "array_id": 6,
            "distribution_spec": [
              "*"
            ],
            "line": 173
          },
          {
            "array_id": 8,
            "distribution_spec": [
              "*"
            ],
            "line": 215
          },
          {
            "array_id": 10,
            "distribution_spec": [
              "*"
            ],
            "line": 259
          },
          {
            "array_id": 12,
            "distribution_spec": [
              "*"
            ],
            "line": 298
          },
          {
            "array_id": 14,
            "distribution_spec": [
              "*"
            ],
            "line": 344
          },
          {
            "array_id": 16,
            "distribution_spec": [
              "*"
            ],
            "line": 388
          },
          {
            "array_id": 18,
            "distribution_spec": [
              "*"
            ],
            "line": 432
          },
          {
            "array_id": 20,
            "distribution_spec": [
              "*"
            ],
            "line": 478
          },
          {
            "array_id": 22,
            "distribution_spec": [
              "*"
            ],
            "line": 526
          },
          {
            "array_id": 24,
            "distribution_spec": [
              "*"
            ],
            "line": 575
          },
          {
            "array_id": 26,
            "distribution_spec": [
              "*"
            ],
            "line": 638
          },
          {
            "array_id": 30,
            "distribution_spec": [
              "*"
            ],
            "line": 703
          },
          {
            "array_id": 32,
            "distribution_spec": [
              "*"
            ],
            "line": 773
          }
        ],
        "parallel": [
          {
            "acrosses": [],
            "computational_intensity": 1.0,
            "iterations_count": [
              1
            ],
            "line": 66,
            "loops_count": 1,
            "reductions": [],
            "remote_accesses": [],
            "shadow_renews": []
          },
          {
            "acrosses": [],
            "computational_intensity": 1.0,
            "iterations_count": [
              1
            ],
            "line": 71,
            "loops_count": 1,
            "reductions": [
              0
            ],
            "remote_accesses": [],
            "shadow_renews": []
          },
          {
            "acrosses": [],
            "computational_intensity": 1.0,
            "iterations_count": [
              1
            ],
            "line": 104,
            "loops_count": 1,
            "reductions": [],
            "remote_accesses": [],
            "shadow_renews": []
          },
          {
            "acrosses": [],
            "computational_intensity": 1.0,
            "iterations_count": [
              1
            ],
            "line": 109,
            "loops_count": 1,
            "reductions": [
              1
            ],
            "remote_accesses": [],
            "shadow_renews": []
          },
          {
            "acrosses": [],
            "computational_intensity": 1.0,
            "iterations_count": [
              17
            ],
            "line": 136,
            "loops_count": 1,
            "reductions": [],
            "remote_accesses": [],
            "shadow_renews": []
          },
          {
            "acrosses": [],
            "computational_intensity": 0.0,
            "iterations_count": [
              16
            ],
            "line": 150,
            "loops_count": 1,
            "reductions": [
              2
            ],
            "remote_accesses": [],
            "shadow_renews": []
          },
          {
            "acrosses": [],
            "computational_intensity": 1.0,
            "iterations_count": [
              17
            ],
            "line": 178,
            "loops_count": 1,
            "reductions": [],
            "remote_accesses": [],
            "shadow_renews": []
          },
          {
            "acrosses": [],
            "computational_intensity": 0.0,
            "iterations_count": [
              16
            ],
            "line": 192,
            "loops_count": 1,
            "reductions": [
              3
            ],
            "remote_accesses": [],
            "shadow_renews": []
          },
          {
            "acrosses": [],
            "computational_intensity": 1.0,
            "iterations_count": [
              17
            ],
            "line": 220,
            "loops_count": 1,
            "reductions": [],
            "remote_accesses": [],
            "shadow_renews": []
          },
          {
            "acrosses": [],
            "computational_intensity": 0.0,
            "iterations_count": [
              16
            ],
            "line": 234,
            "loops_count": 1,
            "reductions": [
              4
            ],
            "remote_accesses": [],
            "shadow_renews": []
          },
          {
            "acrosses": [],
            "computational_intensity": 1.0,
            "iterations_count": [
              1
            ],
            "line": 270,
            "loops_count": 1,
            "reductions": [],
            "remote_accesses": [],
            "shadow_renews": []
          },
          {
            "acrosses": [],
            "computational_intensity": 1.0,
            "iterations_count": [
              1
            ],
            "line": 275,
            "loops_count": 1,
            "reductions": [
              5
            ],
            "remote_accesses": [],
            "shadow_renews": []
          },
          {
            "acrosses": [],
            "computational_intensity": 0.0,
            "iterations_count": [
              1
            ],
            "line": 306,
            "loops_count": 1,
            "reductions": [],
            "remote_accesses": [],
            "shadow_renews": []
          },
          {
            "acrosses": [],
            "computational_intensity": 1.0,
            "iterations_count": [
              8
            ],
            "line": 311,
            "loops_count": 1,
            "reductions": [],
            "remote_accesses": [],
            "shadow_renews": []
          },
          {
            "acrosses": [],
            "computational_intensity": 0.0,
            "iterations_count": [
              16
            ],
            "line": 321,
            "loops_count": 1,
            "reductions": [
              6
            ],
            "remote_accesses": [],
            "shadow_renews": []
          },
          {
            "acrosses": [],
            "computational_intensity": 0.0,
            "iterations_count": [
              1
            ],
            "line": 351,
            "loops_count": 1,
            "reductions": [],
            "remote_accesses": [],
            "shadow_renews": []
          },
          {
            "acrosses": [],
            "computational_intensity": 1.0,
            "iterations_count": [
              8
            ],
            "line": 356,
            "loops_count": 1,
            "reductions": [],
            "remote_accesses": [],
            "shadow_renews": []
          },
          {
            "acrosses": [],
            "computational_intensity": 0.0,
            "iterations_count": [
              16
            ],
            "line": 366,
            "loops_count": 1,
            "reductions": [
              7
            ],
            "remote_accesses": [],
            "shadow_renews": []
          },
          {
            "acrosses": [],
            "computational_intensity": 0.0,
            "iterations_count": [
              1
            ],
            "line": 395,
            "loops_count": 1,
            "reductions": [],
            "remote_accesses": [],
            "shadow_renews": []
          },
          {
            "acrosses": [],
            "computational_intensity": 1.0,
            "iterations_count": [
              8
            ],
            "line": 400,
            "loops_count": 1,
            "reductions": [],
            "remote_accesses": [],
            "shadow_renews": []
          },
          {
            "acrosses": [],
            "computational_intensity": 0.0,
            "iterations_count": [
              16
            ],
            "line": 410,
            "loops_count": 1,
            "reductions": [
              8
            ],
            "remote_accesses": [],
            "shadow_renews": []
          },
          {
            "acrosses": [],
            "computational_intensity": 0.0,
            "iterations_count": [
              1
            ],
            "line": 439,
            "loops_count": 1,
            "reductions": [],
            "remote_accesses": [],
            "shadow_renews": []
          },
          {
            "acrosses": [],
            "computational_intensity": 1.0,
            "iterations_count": [
              8
            ],
            "line": 444,
            "loops_count": 1,
            "reductions": [],
            "remote_accesses": [],
            "shadow_renews": []
          },
          {
            "acrosses": [],
            "computational_intensity": 0.0,
            "iterations_count": [
              16
            ],
            "line": 454,
            "loops_count": 1,
            "reductions": [
              9
            ],
            "remote_accesses": [],
            "shadow_renews": []
          },
          {
            "acrosses": [],
            "computational_intensity": 1.0,
            "iterations_count": [
              17
            ],
            "line": 483,
            "loops_count": 1,
            "reductions": [],
            "remote_accesses": [],
            "shadow_renews": []
          },
          {
            "acrosses": [],
            "computational_intensity": 0.0,
            "iterations_count": [
              16
            ],
            "line": 499,
            "loops_count": 1,
            "reductions": [],
            "remote_accesses": [],
            "shadow_renews": []
          },
          {
            "acrosses": [],
            "computational_intensity": 1.0,
            "iterations_count": [
              17
            ],
            "line": 531,
            "loops_count": 1,
            "reductions": [],
            "remote_accesses": [],
            "shadow_renews": []
          },
          {
            "acrosses": [],
            "computational_intensity": 0.0,
            "iterations_count": [
              16
            ],
            "line": 547,
            "loops_count": 1,
            "reductions": [],
            "remote_accesses": [],
            "shadow_renews": []
          },
          {
            "acrosses": [],
            "computational_intensity": 1.0,
            "iterations_count": [
              17
            ],
            "line": 583,
            "loops_count": 1,
            "reductions": [],
            "remote_accesses": [],
            "shadow_renews": []
          },
          {
            "acrosses": [],
            "computational_intensity": 0.2,
            "iterations_count": [
              17
            ],
            "line": 606,
            "loops_count": 1,
            "reductions": [
              10,
              11,
              12
            ],
            "remote_accesses": [],
            "shadow_renews": []
          },
          {
            "acrosses": [],
            "computational_intensity": 0.0,
            "iterations_count": [
              1
            ],
            "line": 649,
            "loops_count": 1,
            "reductions": [],
            "remote_accesses": [],
            "shadow_renews": []
          },
          {
            "acrosses": [],
            "computational_intensity": 1.0,
            "iterations_count": [
              8
            ],
            "line": 654,
            "loops_count": 1,
            "reductions": [],
            "remote_accesses": [],
            "shadow_renews": []
          },
          {
            "acrosses": [],
            "computational_intensity": 1.0,
            "iterations_count": [
              17
            ],
            "line": 665,
            "loops_count": 1,
            "reductions": [],
            "remote_accesses": [],
            "shadow_renews": []
          },
          {
            "acrosses": [],
            "computational_intensity": 0.5,
            "iterations_count": [
              1
            ],
            "line": 670,
            "loops_count": 1,
            "reductions": [
              13,
              14
            ],
            "remote_accesses": [],
            "shadow_renews": []
          },
          {
            "acrosses": [],
            "computational_intensity": 1.0,
            "iterations_count": [
              17
            ],
            "line": 708,
            "loops_count": 1,
            "reductions": [],
            "remote_accesses": [],
            "shadow_renews": []
          },
          {
            "acrosses": [],
            "computational_intensity": 0.0,
            "iterations_count": [
              17
            ],
            "line": 735,
            "loops_count": 1,
            "reductions": [
              15
            ],
            "remote_accesses": [],
            "shadow_renews": []
          },
          {
            "acrosses": [],
            "computational_intensity": 1.0,
            "iterations_count": [
              17
            ],
            "line": 780,
            "loops_count": 1,
            "reductions": [],
            "remote_accesses": [],
            "shadow_renews": []
          },
          {
            "acrosses": [],
            "computational_intensity": 0.2,
            "iterations_count": [
              17
            ],
            "line": 808,
            "loops_count": 1,
            "reductions": [
              16
            ],
            "remote_accesses": [],
            "shadow_renews": []
          }
        ],
        "reduction": [
          {
            "elements_count": 1,
            "line": 71,
            "operation": "sum",
            "reduction_type": "SCALAR",
            "size_bytes": 4
          },
          {
            "elements_count": 1,
            "line": 109,
            "operation": "product",
            "reduction_type": "SCALAR",
            "size_bytes": 4
          },
          {
            "elements_count": 1,
            "line": 150,
            "operation": "max",
            "reduction_type": "SCALAR",
            "size_bytes": 4
          },
          {
            "elements_count": 1,
            "line": 192,
            "operation": "min",
            "reduction_type": "SCALAR",
            "size_bytes": 4
          },
          {
            "elements_count": 1,
            "line": 234,
            "operation": "max",
            "reduction_type": "SCALAR",
            "size_bytes": 4
          },
          {
            "elements_count": 1,
            "line": 275,
            "operation": "product",
            "reduction_type": "SCALAR",
            "size_bytes": 4
          },
          {
            "elements_count": 1,
            "line": 321,
            "operation": "and",
            "reduction_type": "SCALAR",
            "size_bytes": 4
          },
          {
            "elements_count": 1,
            "line": 366,
            "operation": "or",
            "reduction_type": "SCALAR",
            "size_bytes": 4
          },
          {
            "elements_count": 1,
            "line": 410,
            "operation": "eqv",
            "reduction_type": "SCALAR",
            "size_bytes": 4
          },
          {
            "elements_count": 1,
            "line": 454,
            "operation": "neqv",
            "reduction_type": "SCALAR",
            "size_bytes": 4
          },
          {
            "elements_count": 1,
            "line": 606,
            "operation": "max",
            "reduction_type": "SCALAR",
            "size_bytes": 4
          },
          {
            "elements_count": 1,
            "line": 606,
            "operation": "min",
            "reduction_type": "SCALAR",
            "size_bytes": 4
          },
          {
            "elements_count": 1,
            "line": 606,
            "operation": "sum",
            "reduction_type": "SCALAR",
            "size_bytes": 4
          },
          {
            "elements_count": 1,
            "line": 670,
            "operation": "and",
            "reduction_type": "SCALAR",
            "size_bytes": 4
          },
          {
            "elements_count": 1,
            "line": 670,
            "operation": "product",
            "reduction_type": "SCALAR",
            "size_bytes": 4
          },
          {
            "elements_count": 1,
            "line": 735,
            "operation": "max",
            "reduction_type": "SCALAR",
            "size_bytes": 4
          },
          {
            "elements_count": 1,
            "line": 808,
            "operation": "sum",
            "reduction_type": "SCALAR",
            "size_bytes": 4
          }
        ],
        "remote_access": null,
        "shadow_renew": null
      },
      "launch_grid": {
        "dimensions": [
          0,
          0,
          0
        ],
        "total_processes": 0
      },
      "parallel_execution_fraction": 0.38141361256544504,
      "sequential_execution_time_sec": 0.0
    }
  }
]
