[
  {
    "cluster_info": {
      "cores_per_node": 0,
      "memory_per_node_gb": 0,
      "network_bandwidth_gbps": 0,
      "network_latency_ms": 0,
      "num_nodes": 0,
      "threads_per_node": 0
    }
  },
  {
    "program_info": {
      "arrays_info": [
        {
          "dimensions": [
            100,
            100
          ],
          "element_size_bytes": 4,
          "name": "f0_26_a"
        },
        {
          "dimensions": [
            100,
            100
          ],
          "element_size_bytes": 4,
          "name": "f0_26_as"
        },
        {
          "dimensions": [
            100,
            100
          ],
          "element_size_bytes": 4,
          "name": "f0_26_b"
        },
        {
          "dimensions": [
            100,
            100
          ],
          "element_size_bytes": 4,
          "name": "f0_26_bs"
        },
        {
          "dimensions": [
            100,
            100
          ],
          "element_size_bytes": 4,
          "name": "f0_91_a"
        },
        {
          "dimensions": [
            100,
            100
          ],
          "element_size_bytes": 4,
          "name": "f0_91_as"
        },
        {
          "dimensions": [
            100,
            100
          ],
          "element_size_bytes": 4,
          "name": "f0_91_b"
        },
        {
          "dimensions": [
            100,
            100
          ],
          "element_size_bytes": 4,
          "name": "f0_91_bs"
        },
        {
          "dimensions": [
            100,
            100
          ],
          "element_size_bytes": 4,
          "name": "f0_158_a"
        },
        {
          "dimensions": [
            100,
            100
          ],
          "element_size_bytes": 4,
          "name": "f0_158_as"
        },
        {
          "dimensions": [
            100,
            100
          ],
          "element_size_bytes": 4,
          "name": "f0_158_b"
        },
        {
          "dimensions": [
            100,
            100
          ],
          "element_size_bytes": 4,
          "name": "f0_158_bs"
        },
        {
          "dimensions": [
            100,
            100
          ],
          "element_size_bytes": 4,
          "name": "f0_229_a"
        },
        {
          "dimensions": [
            100,
            100
          ],
          "element_size_bytes": 4,
          "name": "f0_229_as"
        },
        {
          "dimensions": [
            100,
            100
          ],
          "element_size_bytes": 4,
          "name": "f0_229_b"
        },
        {
          "dimensions": [
            100,
            100
          ],
          "element_size_bytes": 4,
          "name": "f0_229_bs"
        }
      ],
      "average_parallel_line_executions": 7729.481481481482,
      "directives": {
        "across": [
          {
            "array_id": 8,
            "communication_pattern": "NEAREST_NEIGHBOR",
            "line": 198,
            "width": [
              [
                0,
                1,
                1
              ],
              [
                1,
                1,
                1
              ]
            ]
          },
          {
            "array_id": 10,
            "communication_pattern": "NEAREST_NEIGHBOR",
            "line": 198,
            "width": [
              [
                0,
                1,
                2
              ],
              [
                1,
                0,
                0
              ]
            ]
          },
          {
            "array_id": 12,
            "communication_pattern": "NEAREST_NEIGHBOR",
            "line": 269,
            "width": [
              [
                0,
                1,
                1
              ],
              [
                1,
                1,
                1
              ]
            ]
          },
          {
            "array_id": 14,
            "communication_pattern": "NEAREST_NEIGHBOR",
            "line": 269,
            "width": [
              [
                0,
                2,
                0
              ],
              [
                1,
                0,
                0
              ]
            ]
          }
        ],
        "parallel": [
          {
            "acrosses": [],
            "computational_intensity": 0.5,
            "iterations_count": [
              1,
              100
            ],
            "line": 49,
            "loops_count": 2,
            "reductions": [],
            "remote_accesses": [],
            "shadow_renews": []
          },
          {
            "acrosses": [],
            "computational_intensity": 1.4,
            "iterations_count": [
              0,
              98
            ],
            "line": 60,
            "loops_count": 2,
            "reductions": [],
            "remote_accesses": [],
            "shadow_renews": []
          },
          {
            "acrosses": [],
            "computational_intensity": 0.75,
            "iterations_count": [
              1,
              98
            ],
            "line": 67,
            "loops_count": 2,
            "reductions": [
              0
            ],
            "remote_accesses": [],
            "shadow_renews": []
          },
          {
            "acrosses": [],
            "computational_intensity": 1.0,
            "iterations_count": [
              1,
              100
            ],
            "line": 114,
            "loops_count": 2,
            "reductions": [],
            "remote_accesses": [],
            "shadow_renews": []
          },
          {
            "acrosses": [],
            "computational_intensity": 1.4444444444444444,
            "iterations_count": [
              0,
              98
            ],
            "line": 127,
            "loops_count": 2,
            "reductions": [],
            "remote_accesses": [],
            "shadow_renews": []
          },
          {
            "acrosses": [],
            "computational_intensity": 0.75,
            "iterations_count": [
              1,
              98
            ],
            "line": 136,
            "loops_count": 2,
            "reductions": [
              1
            ],
            "remote_accesses": [],
            "shadow_renews": []
          },
          {
            "acrosses": [],
            "computational_intensity": 0.75,
            "iterations_count": [
              1,
              100
            ],
            "line": 184,
            "loops_count": 2,
            "reductions": [],
            "remote_accesses": [],
            "shadow_renews": []
          },
          {
            "acrosses": [],
            "computational_intensity": 1.2222222222222223,
            "iterations_count": [
              0,
              97
            ],
            "line": 198,
            "loops_count": 2,
            "reductions": [],
            "remote_accesses": [],
            "shadow_renews": [
              0,
              1
            ]
          },
          {
            "acrosses": [],
            "computational_intensity": 0.75,
            "iterations_count": [
              1,
              100
            ],
            "line": 206,
            "loops_count": 2,
            "reductions": [
              2
            ],
            "remote_accesses": [],
            "shadow_renews": []
          },
          {
            "acrosses": [],
            "computational_intensity": 0.75,
            "iterations_count": [
              1,
              100
            ],
            "line": 255,
            "loops_count": 2,
            "reductions": [],
            "remote_accesses": [],
            "shadow_renews": []
          },
          {
            "acrosses": [],
            "computational_intensity": 1.3333333333333333,
            "iterations_count": [
              0,
              98
            ],
            "line": 269,
            "loops_count": 2,
            "reductions": [],
            "remote_accesses": [],
            "shadow_renews": [
              2,
              3
            ]
          },
          {
            "acrosses": [],
            "computational_intensity": 0.75,
            "iterations_count": [
              1,
              100
            ],
            "line": 277,
            "loops_count": 2,
            "reductions": [
              3
            ],
            "remote_accesses": [],
            "shadow_renews": []
          }
        ],
        "reduction": [
          {
            "elements_count": 1,
            "line": 67,
            "operation": "min",
            "reduction_type": "SCALAR",
            "size_bytes": 4
          },
          {
            "elements_count": 1,
            "line": 136,
            "operation": "min",
            "reduction_type": "SCALAR",
            "size_bytes": 4
          },
          {
            "elements_count": 1,
            "line": 206,
            "operation": "min",
            "reduction_type": "SCALAR",
            "size_bytes": 4
          },
          {
            "elements_count": 1,
            "line": 277,
            "operation": "min",
            "reduction_type": "SCALAR",
            "size_bytes": 4
          }
        ],
        "remote_access": null,
        "shadow_renew": null
      },
      "launch_grid": {
        "dimensions": [
          0,
          0,
          0
        ],
        "total_processes": 0
      },
      "parallel_execution_fraction": 0.610116373572616,
      "sequential_execution_time_sec": 0.0
    }
  }
]
